linter_cli/__init__.py
linter_cli/cli.py
linter_cli/formatters/__init__.py
linter_cli/formatters/python_formatter.py
linter_cli/formatters/yaml_formatter.py
linter_cli/linters/__init__.py
linter_cli/linters/python_linter.py
linter_cli/linters/yaml_linter.py
tests/__init__.py
tests/conftest.py
tests/test_cli.py
tests/test_python.py
tests/test_yaml.py
lintmate-0.1.0.dist-info/LICENSE
lintmate-0.1.0.dist-info/METADATA
lintmate-0.1.0.dist-info/WHEEL
lintmate-0.1.0.dist-info/entry_points.txt
lintmate-0.1.0.dist-info/top_level.txt
lintmate-0.1.0.dist-info/RECORD
