Metadata-Version: 2.1
Name: lintmate
Version: 0.1.0
Summary: A CLI tool for linting and formatting files. Without worying about any dependencies.
Home-page: https://github.com/thesujai/linter-cli
Author: thesujai
Author-email: sujayscience1234@gmail.com
Classifier: Programming Language :: Python :: 3
Classifier: License :: OSI Approved :: MIT License
Classifier: Operating System :: OS Independent
Requires-Python: >=3.9
License-File: LICENSE
Requires-Dist: click==8.1.7
Provides-Extra: python
Requires-Dist: flake8==7.1.0; extra == "python"
Requires-Dist: black==24.8.0; extra == "python"
Provides-Extra: yaml
Requires-Dist: yamllint==1.35.1; extra == "yaml"
Requires-Dist: PyYAML==6.0.1; extra == "yaml"
Requires-Dist: ruamel.yaml==0.18.6; extra == "yaml"
